README.md
setup.py
talha/__init__.py
talha/main.py
talha.egg-info/PKG-INFO
talha.egg-info/SOURCES.txt
talha.egg-info/dependency_links.txt
talha.egg-info/top_level.txt
test/__init__.py
test/test_main.py