Metadata-Version: 2.1
Name: talha
Version: 0.1.0
Summary: Description of your package
Home-page: https://github.com/your_username/your_package_name
Author: Your Name
Author-email: your@email.com
License: UNKNOWN
Platform: UNKNOWN
Classifier: Programming Language :: Python :: 3
